jijzeptlab_mathjax/__init__.py
jijzeptlab_mathjax/_version.py
jijzeptlab_mathjax-0.1.1.data/data/share/jupyter/labextensions/jijzeptlab-mathjax/build_log.json
jijzeptlab_mathjax-0.1.1.data/data/share/jupyter/labextensions/jijzeptlab-mathjax/package.json
jijzeptlab_mathjax-0.1.1.data/data/share/jupyter/labextensions/jijzeptlab-mathjax/schemas/jijzeptlab-mathjax/package.json.orig
jijzeptlab_mathjax-0.1.1.data/data/share/jupyter/labextensions/jijzeptlab-mathjax/schemas/jijzeptlab-mathjax/plugin.json
jijzeptlab_mathjax-0.1.1.data/data/share/jupyter/labextensions/jijzeptlab-mathjax/static/1cb1c39ea642f26a4dfed230b4aea1c3c218689421f6e9c0a7c1811693c4fa07.woff
jijzeptlab_mathjax-0.1.1.data/data/share/jupyter/labextensions/jijzeptlab-mathjax/static/32792104b5ef69eded905b6d1598ed05d8087684d38e7a94d52e3c38ba16f47e.woff
jijzeptlab_mathjax-0.1.1.data/data/share/jupyter/labextensions/jijzeptlab-mathjax/static/355254db9ca10a09a3b5f0929d74eb4670f44fbe864c07526a06213e0a0caf6c.woff
jijzeptlab_mathjax-0.1.1.data/data/share/jupyter/labextensions/jijzeptlab-mathjax/static/3de784d07b9fa8f104c10928a878ee879cf3305cae5195cba663c9c2bb0195eb.woff
jijzeptlab_mathjax-0.1.1.data/data/share/jupyter/labextensions/jijzeptlab-mathjax/static/721921bab0d001ebff0206c24cb5de6ca136467bf1843a7aa32030ba061d1e92.woff
jijzeptlab_mathjax-0.1.1.data/data/share/jupyter/labextensions/jijzeptlab-mathjax/static/870673df72e70f87c91a5a317d558c2c3b54392264ad79bbadc6d424ae8765fe.woff
jijzeptlab_mathjax-0.1.1.data/data/share/jupyter/labextensions/jijzeptlab-mathjax/static/88b98cad3688915e50da55553ff6ad185e0dce134b47f176e91b100f8a9b175c.woff
jijzeptlab_mathjax-0.1.1.data/data/share/jupyter/labextensions/jijzeptlab-mathjax/static/8ea8dbb1b02e6f730f55b4cb5d413b785b9f5c39807d0a0fa7da206a0824a457.woff
jijzeptlab_mathjax-0.1.1.data/data/share/jupyter/labextensions/jijzeptlab-mathjax/static/a009bea404f7a500ded48f8b9ad9cf16e12504b3195dd9e25975289b8256b0f0.woff
jijzeptlab_mathjax-0.1.1.dist-info/METADATA
jijzeptlab_mathjax-0.1.1.dist-info/WHEEL
jijzeptlab_mathjax-0.1.1.dist-info/licenses/LICENSE
jijzeptlab_mathjax-0.1.1.dist-info/RECORD
