Metadata-Version: 2.1
Name: jijzeptlab_mathjax
Version: 0.1.1
Summary: A JupyterLab extension.
Project-URL: Homepage, https://github.com/github_username/jijzeptlab-mathjax
Project-URL: Bug Tracker, https://github.com/github_username/jijzeptlab-mathjax/issues
Project-URL: Repository, https://github.com/github_username/jijzeptlab-mathjax.git
Author-email: "Jij inc." <s.teramachi@j-ij.com>
License: BSD 3-Clause License
License-File: LICENSE
Classifier: Framework :: Jupyter
Classifier: Framework :: Jupyter :: JupyterLab
Classifier: Framework :: Jupyter :: JupyterLab :: 3
Classifier: Framework :: Jupyter :: JupyterLab :: Extensions
Classifier: Framework :: Jupyter :: JupyterLab :: Extensions :: Prebuilt
Classifier: License :: OSI Approved :: BSD License
Classifier: Programming Language :: Python
Classifier: Programming Language :: Python :: 3
Classifier: Programming Language :: Python :: 3.7
Classifier: Programming Language :: Python :: 3.8
Classifier: Programming Language :: Python :: 3.9
Classifier: Programming Language :: Python :: 3.10
Classifier: Programming Language :: Python :: 3.11
Requires-Python: >=3.7
